[
  {
      "id": "pP45FFRqWErwAZTuiU8h",
      "name": "Básico",
      "active": true,
      "currency": "$",
      "order": 0,
      "value": 0,
      "description": "Administra 1 cola.-Acceso hasta a 3 colaboradores.-Acceso a dashboard Básico de tus atenciones en tiempo real.-Hasta 1 sucursal.-Notificaciones a tus usuarios por costo adicional.*-Encuesta de satisfacción post atención para medir tu CSAT.",
      "periodicity": "monthly",
      "online": true,
      "price": 0,
      "permissions": {
          "configuration.admin.only-survey": false,
          "dashboard.reports.surveys": false,
          "dashboard.attention-queue.view": true,
          "reports.admin.notifications": false,
          "dashboard.indicators.view": true,
          "surveys.admin.add": true,
          "collaborator.module.update": true,
          "dashboard.surveys-consolidated-nps-evolution.view": false,
          "configuration.admin.whatsapp-notify-one": true,
          "dashboard.surveys-consolidated-csat-evolution.view": false,
          "business.main-menu.modules-admin": true,
          "dashboard.reports.surveys-management": false,
          "collaborator.attention.finish": true,
          "configuration.admin.whatsapp-notify-five": true,
          "commerces.admin.limit": 1,
          "business.main-menu.collaborators-admin": true,
          "dashboard.attention-duration-evolution.view": false,
          "dashboard.reports.graphs": false,
          "reports.admin.attentions": false,
          "plan.admin.update": false,
          "surveys.admin.edit": true,
          "client.notify.whatsapp": true,
          "configuration.admin.whatsapp-notify-now": true,
          "executive.admin.download": false,
          "configuration.admin.view": true,
          "dashboard.surveys-management.view": false,
          "reports.admin.surveys": false,
          "user.notification.add": true,
          "configuration.admin.add": true,
          "business.main-menu.queues-admin": true,
          "dashboard.attention-hour-distribution.view": false,
          "business.main-menu.manage-admin": true,
          "configuration.admin.edit": true,
          "collaborator.attention.skip": true,
          "collaborator.attention.attend": true,
          "queues.admin.queue-limit": 50,
          "reports.admin.view": false,
          "business.main-menu.dashboard": true,
          "plan.admin.view": true,
          "executive.admin.view": false,
          "plan.admin.edit": true,
          "dashboard.reports.surveys-consolidated": false,
          "dashboard.attention-time-avg.view": true,
          "dashboard.attention-number-queue.view": false,
          "dashboard.surveys.view": false,
          "dashboard.attention-number-evolution.view": false,
          "business.main-menu.business-resume": false,
          "business.main-menu.configuration": true,
          "dashboard.attention-number.view": true,
          "dashboard.reports.indicators": false,
          "business.main-menu.commerce-admin": true,
          "dashboard.surveys-consolidated.view": false,
          "dashboard.attention-notification.view": true,
          "dashboard.attention-flow.view": false,
          "dashboard.graphs.view": false,
          "surveys.admin.update": true,
          "modules.admin.limit": 5,
          "client.notify.email": false,
          "collaborators.admin.limit": 3,
          "business.main-menu.your-plan": true,
          "surveys.admin.limit": 1,
          "surveys.admin.read": true,
          "business.main-menu.reports": false,
          "surveys.admin.view": true,
          "dashboard.survey-flow.view": false,
          "dashboard.attention-rating-avg.view": true,
          "dashboard.attention-no-device.view": true,
          "queues.admin.limit": 3
      }
  },
  {
      "id": "sfR8OyLOMN8RuWjcPkNV",
      "name": "Pro",
      "active": true,
      "currency": "$",
      "order": 1,
      "value": 0,
      "description": "Administra hasta 3 colas.-Acceso hasta a 5 colaboradores.-Acceso a dashboard PRO de tus atenciones en tiempo real.-Hasta 2 sucursales.-Notificaciones a tus usuarios por costo adicional.*-Encuesta de satisfacción post atención para medir tu CSAT.",
      "periodicity": "monthly",
      "online": true,
      "price": 0,
      "permissions": {
          "configuration.admin.only-survey": false,
          "dashboard.reports.surveys": true,
          "dashboard.attention-queue.view": true,
          "reports.admin.notifications": true,
          "dashboard.indicators.view": true,
          "surveys.admin.add": true,
          "collaborator.module.update": true,
          "dashboard.surveys-consolidated-nps-evolution.view": true,
          "configuration.admin.whatsapp-notify-one": true,
          "dashboard.surveys-consolidated-csat-evolution.view": true,
          "business.main-menu.modules-admin": true,
          "dashboard.reports.surveys-management": true,
          "collaborator.attention.finish": true,
          "configuration.admin.whatsapp-notify-five": true,
          "commerces.admin.limit": 3,
          "business.main-menu.collaborators-admin": true,
          "dashboard.attention-duration-evolution.view": true,
          "dashboard.reports.graphs": true,
          "reports.admin.attentions": true,
          "plan.admin.update": false,
          "surveys.admin.edit": true,
          "client.notify.whatsapp": true,
          "executive.admin.download": false,
          "configuration.admin.whatsapp-notify-now": true,
          "configuration.admin.view": true,
          "dashboard.surveys-management.view": true,
          "reports.admin.surveys": true,
          "user.notification.add": true,
          "configuration.admin.add": false,
          "business.main-menu.queues-admin": true,
          "dashboard.attention-hour-distribution.view": true,
          "business.main-menu.manage-admin": true,
          "configuration.admin.edit": true,
          "collaborator.attention.skip": true,
          "collaborator.attention.attend": true,
          "queues.admin.queue-limit": 100,
          "business.main-menu.dashboard": true,
          "reports.admin.view": true,
          "plan.admin.view": true,
          "executive.admin.view": false,
          "plan.admin.edit": true,
          "dashboard.reports.surveys-consolidated": true,
          "dashboard.attention-time-avg.view": true,
          "dashboard.attention-number-queue.view": true,
          "dashboard.surveys.view": true,
          "business.main-menu.business-resume": false,
          "business.main-menu.configuration": true,
          "dashboard.attention-number-evolution.view": true,
          "dashboard.attention-number.view": true,
          "dashboard.reports.indicators": true,
          "business.main-menu.commerce-admin": true,
          "dashboard.surveys-consolidated.view": true,
          "dashboard.attention-notification.view": true,
          "dashboard.attention-flow.view": true,
          "dashboard.graphs.view": true,
          "surveys.admin.update": true,
          "modules.admin.limit": 5,
          "client.notify.email": false,
          "collaborators.admin.limit": 5,
          "business.main-menu.your-plan": true,
          "surveys.admin.limit": 2,
          "surveys.admin.read": true,
          "business.main-menu.reports": true,
          "surveys.admin.view": true,
          "dashboard.survey-flow.view": true,
          "dashboard.attention-rating-avg.view": true,
          "dashboard.attention-no-device.view": true,
          "queues.admin.limit": 5
      }
  },
  {
      "id": "P8AWIwgTueWktnCwsQwZ",
      "name": "Premium",
      "active": true,
      "currency": "$",
      "order": 2,
      "value": 0,
      "description": "Administra hasta 10 colas.-Acceso hasta a 10 colaboradores.-Acceso a dashboard PREMIUM de tus atenciones en tiempo real.-Hasta 5 sucursales.-Notificaciones a tus usuarios por costo adicional.*-Encuesta de satisfacción post atención para medir tu CSAT.",
      "periodicity": "monthly",
      "online": true,
      "price": 0,
      "permissions": {
          "configuration.admin.only-survey": true,
          "dashboard.reports.surveys": true,
          "dashboard.attention-queue.view": true,
          "reports.admin.notifications": true,
          "dashboard.indicators.view": true,
          "surveys.admin.add": true,
          "collaborator.module.update": true,
          "dashboard.surveys-consolidated-nps-evolution.view": true,
          "configuration.admin.whatsapp-notify-one": true,
          "dashboard.surveys-consolidated-csat-evolution.view": true,
          "business.main-menu.modules-admin": true,
          "dashboard.reports.surveys-management": true,
          "collaborator.attention.finish": true,
          "configuration.admin.whatsapp-notify-five": true,
          "commerces.admin.limit": 5,
          "business.main-menu.collaborators-admin": true,
          "dashboard.attention-duration-evolution.view": true,
          "dashboard.reports.graphs": true,
          "reports.admin.attentions": true,
          "plan.admin.update": true,
          "surveys.admin.edit": true,
          "client.notify.whatsapp": true,
          "configuration.admin.whatsapp-notify-now": true,
          "executive.admin.download": true,
          "configuration.admin.view": true,
          "dashboard.surveys-management.view": true,
          "reports.admin.surveys": true,
          "user.notification.add": true,
          "configuration.admin.add": true,
          "business.main-menu.queues-admin": true,
          "dashboard.attention-hour-distribution.view": true,
          "business.main-menu.manage-admin": true,
          "configuration.admin.edit": true,
          "collaborator.attention.skip": true,
          "collaborator.attention.attend": true,
          "queues.admin.queue-limit": 200,
          "reports.admin.view": true,
          "business.main-menu.dashboard": true,
          "plan.admin.view": true,
          "executive.admin.view": true,
          "plan.admin.edit": true,
          "dashboard.reports.surveys-consolidated": true,
          "dashboard.attention-time-avg.view": true,
          "dashboard.attention-number-queue.view": true,
          "dashboard.surveys.view": true,
          "dashboard.attention-number-evolution.view": true,
          "business.main-menu.business-resume": true,
          "business.main-menu.configuration": true,
          "dashboard.attention-number.view": true,
          "dashboard.reports.indicators": true,
          "business.main-menu.commerce-admin": true,
          "dashboard.surveys-consolidated.view": true,
          "dashboard.attention-notification.view": true,
          "dashboard.attention-flow.view": true,
          "dashboard.graphs.view": true,
          "surveys.admin.update": true,
          "modules.admin.limit": 10,
          "client.notify.email": false,
          "collaborators.admin.limit": 10,
          "business.main-menu.your-plan": true,
          "surveys.admin.read": true,
          "surveys.admin.limit": 5,
          "business.main-menu.reports": true,
          "surveys.admin.view": true,
          "dashboard.survey-flow.view": true,
          "dashboard.attention-rating-avg.view": true,
          "dashboard.attention-no-device.view": true,
          "queues.admin.limit": 5
      }
  },
  {
      "id": "ZN8rXnF82X1ZMjpukNrn",
      "name": "Personalizado",
      "currency": "$",
      "value": 0,
      "active": true,
      "description": "¿Necesitas más capacidades?-Puedes cotizar un plan personalizado que incluya las filas, colaboradores y sucursales que necesita tu empresa.-Contacta con nosotros y construyamos juntos el plan que se adapte a ti.",
      "permissions": {},
      "periodicity": "monthly",
      "order": 3,
      "online": true,
      "price": 0
  },
  {
      "id": "f6u844WBytY9VYIwb6I2",
      "createdAt": "2023-09-12T15:29:41.790Z",
      "value": 0,
      "order": 5,
      "periodicity": "quarterly",
      "name": "Freemium",
      "active": false,
      "permissions": {},
      "price": 0,
      "description": "Administra hasta 3 colas.-Acceso hasta a 3 colaboradores.-Acceso a dashboard Básico de tus atenciones en tiempo real.-Hasta 1 sucursal.-Notificaciones a tus usuarios por costo adicional.*-Encuesta de satisfacción post atención para medir tu CSAT.",
      "online": false
  }
]